puissance4/__init__.py
puissance4/play.py
puissance4/training.py
puissance4/agent/__init__.py
puissance4/agent/ai.py
puissance4/agent/ai_interface.py
puissance4/agent/mc.py
puissance4/agent/uct.py
puissance4/configs/__init__.py
puissance4/configs/parameters.py
puissance4/env/__init__.py
puissance4/env/grille.py
puissance4/env/win_conditions.py
puissance4/lib/__init__.py
puissance4/lib/node.py
puissance4/lib/utils.py
puissance4/tests/__init__.py
puissance4/tests/test_puissance4.py
puissance4-0.6.1.dist-info/LICENSE
puissance4-0.6.1.dist-info/METADATA
puissance4-0.6.1.dist-info/WHEEL
puissance4-0.6.1.dist-info/top_level.txt
puissance4-0.6.1.dist-info/RECORD
