Metadata-Version: 2.1
Name: puissance4
Version: 0.6.1
Summary: Artificial Intelligence for the game Connect Four on PyPI
Home-page: https://github.com/woctezuma/puissance4
Author: Wok
Author-email: wok@tuta.io
License: UNKNOWN
Download-URL: https://github.com/woctezuma/puissance4/archive/0.6.1.tar.gz
Keywords: puissance4,puissance-4,connect4,connect-4,connect-four,artificial intelligence,UCT
Platform: UNKNOWN
Classifier: Development Status :: 5 - Production/Stable
Classifier: Topic :: Games/Entertainment
Classifier: Programming Language :: Python :: 3
Classifier: License :: OSI Approved :: MIT License
Classifier: Operating System :: OS Independent
Classifier: Intended Audience :: End Users/Desktop
Classifier: Natural Language :: French
Requires-Python: >=3
